imgsimilarity/diff.py
imgsimilarity-1.dist-info/LICENSE
imgsimilarity-1.dist-info/METADATA
imgsimilarity-1.dist-info/WHEEL
imgsimilarity-1.dist-info/top_level.txt
imgsimilarity-1.dist-info/RECORD
