Metadata-Version: 2.1
Name: imgsimilarity
Version: 1
Summary: A tool to compare similar images
Home-page: UNKNOWN
Author: Dheeraj As
Author-email: dheeraj.as008@gmail.com
License: UNKNOWN
Project-URL: Source, https://github.com/RealNameHidden/img-diff
Keywords: image similarity dhash
Platform: UNKNOWN
Classifier: License :: OSI Approved :: MIT License
Classifier: Programming Language :: Python :: 3
Classifier: Programming Language :: Python :: 3.5
Classifier: Programming Language :: Python :: 3.6
Classifier: Programming Language :: Python :: 3.7
Classifier: Programming Language :: Python :: 3.8
Classifier: Programming Language :: Python :: 3 :: Only
Requires-Python: >=3.0, <4
Requires-Dist: dhash
Requires-Dist: Pillow
Provides-Extra: dev
Requires-Dist: pytest ; extra == 'dev'
Provides-Extra: test
Requires-Dist: pytest ; extra == 'test'
